{
  "hash": "9f65e53c",
  "configHash": "ca06b8d3",
  "lockfileHash": "ddfa1f94",
  "browserHash": "07a0eaee",
  "optimized": {
    "vue": {
      "src": "../../../../node_modules/.pnpm/vue@3.5.33_typescript@5.9.3/node_modules/vue/dist/vue.runtime.esm-bundler.js",
      "file": "vue.js",
      "fileHash": "1f8fa938",
      "needsInterop": false
    },
    "vitepress > @vue/devtools-api": {
      "src": "../../../../node_modules/.pnpm/@vue+devtools-api@7.7.9/node_modules/@vue/devtools-api/dist/index.js",
      "file": "vitepress___@vue_devtools-api.js",
      "fileHash": "060131e3",
      "needsInterop": false
    },
    "vitepress > @vueuse/core": {
      "src": "../../../../node_modules/.pnpm/@vueuse+core@12.8.2_typescript@5.9.3/node_modules/@vueuse/core/index.mjs",
      "file": "vitepress___@vueuse_core.js",
      "fileHash": "efe31523",
      "needsInterop": false
    },
    "vitepress > @vueuse/integrations/useFocusTrap": {
      "src": "../../../../node_modules/.pnpm/@vueuse+integrations@12.8.2_axios@1.15.0_focus-trap@7.8.0_typescript@5.9.3/node_modules/@vueuse/integrations/useFocusTrap.mjs",
      "file": "vitepress___@vueuse_integrations_useFocusTrap.js",
      "fileHash": "86804fcc",
      "needsInterop": false
    },
    "vitepress > mark.js/src/vanilla.js": {
      "src": "../../../../node_modules/.pnpm/mark.js@8.11.1/node_modules/mark.js/src/vanilla.js",
      "file": "vitepress___mark__js_src_vanilla__js.js",
      "fileHash": "9b4f29b2",
      "needsInterop": false
    },
    "vitepress > minisearch": {
      "src": "../../../../node_modules/.pnpm/minisearch@7.2.0/node_modules/minisearch/dist/es/index.js",
      "file": "vitepress___minisearch.js",
      "fileHash": "40f06a59",
      "needsInterop": false
    },
    "mermaid/dist/mermaid.esm.min.mjs": {
      "src": "../../../../node_modules/.pnpm/mermaid@11.14.0/node_modules/mermaid/dist/mermaid.esm.min.mjs",
      "file": "mermaid_dist_mermaid__esm__min__mjs.js",
      "fileHash": "f250fcfb",
      "needsInterop": false
    }
  },
  "chunks": {
    "diagram-H7BISOXX-GXWRP2YE": {
      "file": "diagram-H7BISOXX-GXWRP2YE.js"
    },
    "blockDiagram-IGV67L2C-ROUNY5Q6": {
      "file": "blockDiagram-IGV67L2C-ROUNY5Q6.js"
    },
    "diagram-LXUTUG65-S7ZFDLGP": {
      "file": "diagram-LXUTUG65-S7ZFDLGP.js"
    },
    "architectureDiagram-EMZXCZ2Q-ZKVAPAFE": {
      "file": "architectureDiagram-EMZXCZ2Q-ZKVAPAFE.js"
    },
    "ishikawaDiagram-YMYX4NHK-OKR5SJQS": {
      "file": "ishikawaDiagram-YMYX4NHK-OKR5SJQS.js"
    },
    "vennDiagram-IE5QUKF5-O2RN4BXX": {
      "file": "vennDiagram-IE5QUKF5-O2RN4BXX.js"
    },
    "diagram-WEHSV5V5-IFR6YJIY": {
      "file": "diagram-WEHSV5V5-IFR6YJIY.js"
    },
    "wardleyDiagram-XU3VSMPF-OUNPJMEE": {
      "file": "wardleyDiagram-XU3VSMPF-OUNPJMEE.js"
    },
    "stateDiagram-MLPALWAM-JW3WLCDW": {
      "file": "stateDiagram-MLPALWAM-JW3WLCDW.js"
    },
    "stateDiagram-v2-B5LQ5ZB2-2IPPVU6V": {
      "file": "stateDiagram-v2-B5LQ5ZB2-2IPPVU6V.js"
    },
    "chunk-KPZWZI5L": {
      "file": "chunk-KPZWZI5L.js"
    },
    "journeyDiagram-SO5T7YLQ-EGEOLCG6": {
      "file": "journeyDiagram-SO5T7YLQ-EGEOLCG6.js"
    },
    "timeline-definition-5SPVSISX-AN433M25": {
      "file": "timeline-definition-5SPVSISX-AN433M25.js"
    },
    "mindmap-definition-2EUWGEK5-6YMWQNAB": {
      "file": "mindmap-definition-2EUWGEK5-6YMWQNAB.js"
    },
    "kanban-definition-LJHFXRCJ-YDYOWYCA": {
      "file": "kanban-definition-LJHFXRCJ-YDYOWYCA.js"
    },
    "sankeyDiagram-L3NBLAOT-MG75WST5": {
      "file": "sankeyDiagram-L3NBLAOT-MG75WST5.js"
    },
    "diagram-JC5VWROH-BSHPEPTD": {
      "file": "diagram-JC5VWROH-BSHPEPTD.js"
    },
    "infoDiagram-MN7RKWGX-6YBUKRHL": {
      "file": "infoDiagram-MN7RKWGX-6YBUKRHL.js"
    },
    "pieDiagram-3IATQBI2-CJ4PS5BJ": {
      "file": "pieDiagram-3IATQBI2-CJ4PS5BJ.js"
    },
    "quadrantDiagram-E256RVCF-WQYLCOZM": {
      "file": "quadrantDiagram-E256RVCF-WQYLCOZM.js"
    },
    "xychartDiagram-ZHJ5623Y-LAMQDAK3": {
      "file": "xychartDiagram-ZHJ5623Y-LAMQDAK3.js"
    },
    "requirementDiagram-M5DCFWZL-HOKTPCHP": {
      "file": "requirementDiagram-M5DCFWZL-HOKTPCHP.js"
    },
    "sequenceDiagram-ZOUHS735-AB3VGV3P": {
      "file": "sequenceDiagram-ZOUHS735-AB3VGV3P.js"
    },
    "classDiagram-PPOCWD7C-C6BX4ZLW": {
      "file": "classDiagram-PPOCWD7C-C6BX4ZLW.js"
    },
    "classDiagram-v2-23LJLIIU-DHW3EGYH": {
      "file": "classDiagram-v2-23LJLIIU-DHW3EGYH.js"
    },
    "chunk-D3EP4QLI": {
      "file": "chunk-D3EP4QLI.js"
    },
    "treeView-SZITEDCU-5DXDK3XO-SM2NYDDD": {
      "file": "treeView-SZITEDCU-5DXDK3XO-SM2NYDDD.js"
    },
    "architecture-YZFGNWBL-S5CXDPWN-N2LX222R": {
      "file": "architecture-YZFGNWBL-S5CXDPWN-N2LX222R.js"
    },
    "gitGraph-7Q5UKJZL-54BCDZD5-KCS6VQM4": {
      "file": "gitGraph-7Q5UKJZL-54BCDZD5-KCS6VQM4.js"
    },
    "radar-PYXPWWZC-P6TP7ZYP-VCVPJJWH": {
      "file": "radar-PYXPWWZC-P6TP7ZYP-VCVPJJWH.js"
    },
    "treemap-W4RFUUIX-WYLRDWKO-WUPKOH6G": {
      "file": "treemap-W4RFUUIX-WYLRDWKO-WUPKOH6G.js"
    },
    "wardley-RL74JXVD-BCRCBASE-2S3ED3WN": {
      "file": "wardley-RL74JXVD-BCRCBASE-2S3ED3WN.js"
    },
    "gitGraphDiagram-3HKGZ4G3-SRPB2HZV": {
      "file": "gitGraphDiagram-3HKGZ4G3-SRPB2HZV.js"
    },
    "chunk-S3XR4SNL": {
      "file": "chunk-S3XR4SNL.js"
    },
    "chunk-PG2EBXFX": {
      "file": "chunk-PG2EBXFX.js"
    },
    "chunk-Z75ON5TC": {
      "file": "chunk-Z75ON5TC.js"
    },
    "chunk-G7CRMAJP": {
      "file": "chunk-G7CRMAJP.js"
    },
    "chunk-EUSCIRG4": {
      "file": "chunk-EUSCIRG4.js"
    },
    "chunk-KDDFP6PK": {
      "file": "chunk-KDDFP6PK.js"
    },
    "chunk-ZJVYFLWS": {
      "file": "chunk-ZJVYFLWS.js"
    },
    "chunk-CGNTNBTA": {
      "file": "chunk-CGNTNBTA.js"
    },
    "chunk-CCKZNSTL": {
      "file": "chunk-CCKZNSTL.js"
    },
    "ganttDiagram-MUNLMDZQ-VKZVRPJH": {
      "file": "ganttDiagram-MUNLMDZQ-VKZVRPJH.js"
    },
    "dagre-E77IOHMT-GLVUPNT2": {
      "file": "dagre-E77IOHMT-GLVUPNT2.js"
    },
    "chunk-M3ZS3LOY": {
      "file": "chunk-M3ZS3LOY.js"
    },
    "chunk-NVNIWB3X": {
      "file": "chunk-NVNIWB3X.js"
    },
    "cose-bilkent-PNC4W37J-PUAFFJYG": {
      "file": "cose-bilkent-PNC4W37J-PUAFFJYG.js"
    },
    "chunk-D7XFU3CV": {
      "file": "chunk-D7XFU3CV.js"
    },
    "c4Diagram-DFAF54RM-EAOBGN5C": {
      "file": "c4Diagram-DFAF54RM-EAOBGN5C.js"
    },
    "flowDiagram-OTCZ4VVT-XJ25LSS3": {
      "file": "flowDiagram-OTCZ4VVT-XJ25LSS3.js"
    },
    "chunk-NFYNFPBA": {
      "file": "chunk-NFYNFPBA.js"
    },
    "chunk-TEJXR2YZ": {
      "file": "chunk-TEJXR2YZ.js"
    },
    "erDiagram-GCSMX5X6-7I3TPPAH": {
      "file": "erDiagram-GCSMX5X6-7I3TPPAH.js"
    },
    "chunk-UDPC2CDO": {
      "file": "chunk-UDPC2CDO.js"
    },
    "chunk-HKRTJANV": {
      "file": "chunk-HKRTJANV.js"
    },
    "info-OMHHGYJF-BF2H5H6G-64RB4QX3": {
      "file": "info-OMHHGYJF-BF2H5H6G-64RB4QX3.js"
    },
    "chunk-LTAWPWJ6": {
      "file": "chunk-LTAWPWJ6.js"
    },
    "packet-4T2RLAQJ-EV4IVRXR-5B7AMRIK": {
      "file": "packet-4T2RLAQJ-EV4IVRXR-5B7AMRIK.js"
    },
    "chunk-VNU3COQH": {
      "file": "chunk-VNU3COQH.js"
    },
    "pie-ZZUOXDRM-N23DN5KN-WFBIN3V6": {
      "file": "pie-ZZUOXDRM-N23DN5KN-WFBIN3V6.js"
    },
    "chunk-2ZIBIWL3": {
      "file": "chunk-2ZIBIWL3.js"
    },
    "chunk-UOHFH3CX": {
      "file": "chunk-UOHFH3CX.js"
    },
    "chunk-3DBRZS4A": {
      "file": "chunk-3DBRZS4A.js"
    },
    "chunk-5UZD3E6K": {
      "file": "chunk-5UZD3E6K.js"
    },
    "chunk-CLSIJVMQ": {
      "file": "chunk-CLSIJVMQ.js"
    },
    "chunk-4S3GMVOJ": {
      "file": "chunk-4S3GMVOJ.js"
    },
    "chunk-YYFVCIEQ": {
      "file": "chunk-YYFVCIEQ.js"
    },
    "chunk-V354F32T": {
      "file": "chunk-V354F32T.js"
    },
    "chunk-QDSNXXJA": {
      "file": "chunk-QDSNXXJA.js"
    },
    "chunk-LK7THHH6": {
      "file": "chunk-LK7THHH6.js"
    },
    "chunk-OB6FDEYX": {
      "file": "chunk-OB6FDEYX.js"
    },
    "chunk-KKUK5XSX": {
      "file": "chunk-KKUK5XSX.js"
    },
    "chunk-37DMPFOG": {
      "file": "chunk-37DMPFOG.js"
    },
    "chunk-BIOJLABG": {
      "file": "chunk-BIOJLABG.js"
    },
    "chunk-GYGMMI4F": {
      "file": "chunk-GYGMMI4F.js"
    },
    "chunk-DZJA65GQ": {
      "file": "chunk-DZJA65GQ.js"
    },
    "chunk-DJX4MEFN": {
      "file": "chunk-DJX4MEFN.js"
    },
    "chunk-HPIGS4CQ": {
      "file": "chunk-HPIGS4CQ.js"
    },
    "chunk-LKDN26KO": {
      "file": "chunk-LKDN26KO.js"
    },
    "chunk-TIOLQL7Q": {
      "file": "chunk-TIOLQL7Q.js"
    },
    "chunk-EQAKJMPU": {
      "file": "chunk-EQAKJMPU.js"
    },
    "katex-GD7MH7QM-X7TSEN5B": {
      "file": "katex-GD7MH7QM-X7TSEN5B.js"
    },
    "chunk-NOL3LC7I": {
      "file": "chunk-NOL3LC7I.js"
    },
    "chunk-V6TY7KAL": {
      "file": "chunk-V6TY7KAL.js"
    }
  }
}